wish_models/__init__.py
wish_models/data.py
wish_models/engagement.py
wish_models/finding.py
wish_models/host.py
wish_models/py.typed
wish_models/session.py
wish_models/validation.py
wish_models-0.7.0.dist-info/METADATA
wish_models-0.7.0.dist-info/WHEEL
wish_models-0.7.0.dist-info/RECORD
